servicenow_mcp_server/__init__.py
servicenow_mcp_server/__main__.py
servicenow_mcp_server/config_loader.py
servicenow_mcp_server/server.py
servicenow_mcp_server/utils.py
servicenow_mcp_server/agile_management/__init__.py
servicenow_mcp_server/agile_management/epic_tools.py
servicenow_mcp_server/agile_management/scrum_tools.py
servicenow_mcp_server/agile_management/story_tools.py
servicenow_mcp_server/analytics/__init__.py
servicenow_mcp_server/analytics/analytics_tools.py
servicenow_mcp_server/change_management/__init__.py
servicenow_mcp_server/change_management/change_tools.py
servicenow_mcp_server/changeset_management/__init__.py
servicenow_mcp_server/changeset_management/changeset_tools.py
servicenow_mcp_server/incident_management/__init__.py
servicenow_mcp_server/incident_management/incident_tools.py
servicenow_mcp_server/kb_management/__init__.py
servicenow_mcp_server/kb_management/kb_tools.py
servicenow_mcp_server/project_management/__init__.py
servicenow_mcp_server/project_management/project_tools.py
servicenow_mcp_server/request_management/__init__.py
servicenow_mcp_server/request_management/request_tools.py
servicenow_mcp_server/script_include_management/__init__.py
servicenow_mcp_server/script_include_management/script_include_tools.py
servicenow_mcp_server/service_catalog/__init__.py
servicenow_mcp_server/service_catalog/catalog_tools.py
servicenow_mcp_server/table_management/__init__.py
servicenow_mcp_server/table_management/table_tools.py
servicenow_mcp_server/ui_policy_management/__init__.py
servicenow_mcp_server/ui_policy_management/ui_policy_tools.py
servicenow_mcp_server/user_management/__init__.py
servicenow_mcp_server/user_management/user_tools.py
servicenow_mcp_server/workflow_management/__init__.py
servicenow_mcp_server/workflow_management/workflow_tools.py
snow_mcp-0.1.1.dist-info/licenses/LICENSE
snow_mcp-0.1.1.dist-info/METADATA
snow_mcp-0.1.1.dist-info/WHEEL
snow_mcp-0.1.1.dist-info/entry_points.txt
snow_mcp-0.1.1.dist-info/top_level.txt
snow_mcp-0.1.1.dist-info/RECORD
